odoo10_addon_account_e_invoice_generate-10.0.1.0.0-py2.7-nspkg.pth
odoo/addons/account_e-invoice_generate/README.rst
odoo/addons/account_e-invoice_generate/__init__.py
odoo/addons/account_e-invoice_generate/__manifest__.py
odoo/addons/account_e-invoice_generate/models/__init__.py
odoo/addons/account_e-invoice_generate/models/account_config_settings.py
odoo/addons/account_e-invoice_generate/models/company.py
odoo/addons/account_e-invoice_generate/views/account_config_settings.xml
odoo10_addon_account_e_invoice_generate-10.0.1.0.0.dist-info/DESCRIPTION.rst
odoo10_addon_account_e_invoice_generate-10.0.1.0.0.dist-info/METADATA
odoo10_addon_account_e_invoice_generate-10.0.1.0.0.dist-info/RECORD
odoo10_addon_account_e_invoice_generate-10.0.1.0.0.dist-info/WHEEL
odoo10_addon_account_e_invoice_generate-10.0.1.0.0.dist-info/metadata.json
odoo10_addon_account_e_invoice_generate-10.0.1.0.0.dist-info/namespace_packages.txt
odoo10_addon_account_e_invoice_generate-10.0.1.0.0.dist-info/top_level.txt
